disarmgears/__init__.py
disarm_gears-0.0.1.dev0.dist-info/METADATA
disarm_gears-0.0.1.dev0.dist-info/WHEEL
disarm_gears-0.0.1.dev0.dist-info/entry_points.txt
disarm_gears-0.0.1.dev0.dist-info/top_level.txt
disarm_gears-0.0.1.dev0.dist-info/RECORD
