Metadata-Version: 2.1
Name: disarm-gears
Version: 0.0.1.dev0
Summary: DiSARM algorithms framework
Home-page: UNKNOWN
Author: UNKNOWN
Author-email: UNKNOWN
License: UNKNOWN
Platform: UNKNOWN
